hookee/__init__.py
hookee/banner.txt
hookee/cli.py
hookee/conf.py
hookee/config_default.yaml
hookee/exception.py
hookee/hookeemanager.py
hookee/pluginmanager.py
hookee/server.py
hookee/tunnel.py
hookee/util.py
hookee/plugins/__init__.py
hookee/plugins/blueprint_default.py
hookee/plugins/request_body.py
hookee/plugins/request_files.py
hookee/plugins/request_headers.py
hookee/plugins/request_query_params.py
hookee/plugins/request_url_info.py
hookee/plugins/response_echo.py
hookee/plugins/response_info.py
hookee-2.3.12.dist-info/licenses/LICENSE
hookee-2.3.12.dist-info/METADATA
hookee-2.3.12.dist-info/WHEEL
hookee-2.3.12.dist-info/entry_points.txt
hookee-2.3.12.dist-info/top_level.txt
hookee-2.3.12.dist-info/RECORD
