Metadata-Version: 2.4
Name: hookee
Version: 2.3.12
Summary: Command line webhooks, on demand
Author-email: Alex Laird <contact@alexlaird.com>
Maintainer-email: Alex Laird <contact@alexlaird.com>
License-Expression: MIT
Project-URL: Changelog, https://github.com/alexdlaird/hookee/blob/main/CHANGELOG.md
Project-URL: Documentation, https://hookee.readthedocs.io
Project-URL: Sponsor, https://github.com/sponsors/alexdlaird
Project-URL: Source Code, https://github.com/alexdlaird/hookee
Classifier: Development Status :: 5 - Production/Stable
Classifier: Environment :: Console
Classifier: Environment :: Web Environment
Classifier: Framework :: Flask
Classifier: Intended Audience :: Developers
Classifier: Intended Audience :: Education
Classifier: Intended Audience :: System Administrators
Classifier: Operating System :: OS Independent
Classifier: Programming Language :: Python :: 3
Classifier: Programming Language :: Python :: 3.9
Classifier: Programming Language :: Python :: 3.10
Classifier: Programming Language :: Python :: 3.11
Classifier: Programming Language :: Python :: 3.12
Classifier: Programming Language :: Python :: 3.13
Classifier: Topic :: Internet :: Proxy Servers
Classifier: Topic :: Internet :: WWW/HTTP :: Dynamic Content
Classifier: Topic :: Internet :: WWW/HTTP :: HTTP Servers
Classifier: Topic :: Software Development :: Testing
Requires-Python: >=3.9
License-File: LICENSE
Requires-Dist: pluginbase>=1.0
Requires-Dist: confuse>=1.3
Requires-Dist: flask>=1.1
Requires-Dist: click>=7.1
Requires-Dist: pyngrok>=7.2
Requires-Dist: defusedxml>=0.6
Provides-Extra: dev
Requires-Dist: pytest; extra == "dev"
Requires-Dist: coverage[toml]; extra == "dev"
Requires-Dist: requests; extra == "dev"
Requires-Dist: flake8; extra == "dev"
Requires-Dist: flake8-pyproject; extra == "dev"
Requires-Dist: pep8-naming; extra == "dev"
Provides-Extra: docs
Requires-Dist: Sphinx; extra == "docs"
Requires-Dist: sphinx-notfound-page; extra == "docs"
Dynamic: license-file
